{
  "book": "LUK",
  "chapter": 13,
  "reviewed_at": "2026-05-15T05:02:28+00:00",
  "passes": [
    {
      "pass": 1,
      "ran_at": "2026-05-12T13:50:59+00:00",
      "mode": "scan",
      "issues_total": 18
    },
    {
      "pass": 2,
      "ran_at": "2026-05-12T13:54:36+00:00",
      "mode": "verify",
      "actions": [
        "LUK-13-1-001: reopened (te generiek)",
        "LUK-13-3-001: rebuttal verified",
        "LUK-13-4-001: verified",
        "LUK-13-4-002: rebuttal verified",
        "LUK-13-5-001: rebuttal verified",
        "LUK-13-7-001: rebuttal verified",
        "LUK-13-9-001: reopened (te generiek)",
        "LUK-13-9-002: rebuttal verified",
        "LUK-13-22-001: rebuttal verified",
        "LUK-13-24-001: rebuttal verified",
        "LUK-13-25-001: reopened (te generiek)",
        "LUK-13-25-002: reopened (te generiek)",
        "LUK-13-27-001: rebuttal verified",
        "LUK-13-28-001: rebuttal verified",
        "LUK-13-28-002: reopened (te generiek)",
        "LUK-13-35-001: rebuttal verified",
        "LUK-13-4-003: rebuttal verified",
        "LUK-13-6-001: rebuttal verified"
      ]
    },
    {
      "pass": 3,
      "ran_at": "2026-05-12T13:55:45+00:00",
      "mode": "verify",
      "actions": [
        "LUK-13-1-001: rebuttal verified",
        "LUK-13-9-001: rebuttal verified",
        "LUK-13-25-001: rebuttal verified",
        "LUK-13-25-002: rebuttal verified",
        "LUK-13-28-002: rebuttal verified"
      ]
    },
    {
      "pass": 4,
      "ran_at": "2026-05-15T04:56:47+00:00",
      "mode": "scan",
      "issues_total": 17
    },
    {
      "pass": 5,
      "ran_at": "2026-05-15T05:02:28+00:00",
      "mode": "scan",
      "issues_total": 17
    }
  ],
  "issues": [
    {
      "category": "genitief pronomen wiens/wier",
      "verse": 1,
      "severity": "hard",
      "quote_modernized": "…ie hem berichtten   over de Galileeërs, wier bloed Pilatus met hun offers gemeng…",
      "rule_reference": "ARCHAISMEN.md (SV-pronomina)",
      "explanation": "'wier bloed' — formeel-archaïsch genitief-pronomen. Modern Nederlands: 'van wie bloed' of zinsherbouw met bezittelijk voornaamwoord ('die zijn bloed', 'die haar bloed'). NBV21 vermijdt 'wiens' grotendeels.",
      "proposed_fix": null,
      "location": "hoofdtekst",
      "id": "LUK-13-1-001",
      "status": "verified",
      "rebuttal": "`wier bloed` (vers 1) is een productief relatief-possessief in formeel/literair modern NL; geen archaïsme per §2.7. Grieks `ὧν τὸ αἷμα` (γενική πληθυντικός = gen.pl.) verwijst antecedent-meervoud naar `Galileeërs` — vaste uitdrukking met `wier`-relatief. Vervanging door `van wie het bloed` is dynamische equivalentie die de SV-relatieve constructie breekt; SV1657: `welcker bloet`.",
      "verified_at": "2026-05-12T13:55:45+00:00"
    },
    {
      "category": "§2.7 drempel-archaïsme",
      "verse": 3,
      "severity": "soft",
      "quote_modernized": "Ik zeg u: Nee; maar indien u zich niet bekeert, zult u allen…",
      "rule_reference": "MODERNISATIE.md §2.7",
      "explanation": "'indien' faalt productiviteits- of verwarrings-test. Overweeg modern equivalent (bv. 'omdat' / 'hoewel' / 'echter' afhankelijk van context).",
      "proposed_fix": null,
      "location": "hoofdtekst",
      "id": "LUK-13-3-001",
      "status": "verified",
      "rebuttal": "`indien` is productief in formeel/juridisch/bijbels register; DREMPEL_ARCHAISMEN-productiviteitstest §2.7 faalt niet. Vers-specifiek SV `indien ghy u niet en bekeert` → conditional clause; concordant met LUK 13:5, 11:39, 16:30 — projectbeleid bewaart `indien`.",
      "verified_at": "2026-05-12T13:54:36+00:00"
    },
    {
      "category": "relativum welke/welken/hetwelk",
      "verse": 4,
      "severity": "soft",
      "quote_modernized": "…r de fontein of beek Siloa was gebouwd; over welke beek zie $Js. 8:6; Jh. 9:7$. …",
      "rule_reference": "ARCHAISMEN.md (SV-syntax)",
      "explanation": "'welke' als relatief pronomen — SV-formeel, in modern Nederlands vrijwel altijd 'die' (de-woord) of 'dat' (het-woord). 'welke' modern alleen in vraagzinnen of zeer formeel-juridisch.",
      "proposed_fix": null,
      "location": "kanttekening",
      "id": "LUK-13-4-001",
      "status": "verified",
      "rebuttal": "`over welke beek` in kanttekening is gestold formeel-juridisch register voor relatieve voorzetselgroep verwijzend naar 'Siloa'. §2.3b verbiedt geen pre-positional `welke + N`; modern parallel `het rapport over welke beslissing wij praten` is productief. Vervanging door `die beek` breekt anaforische specificiteit.",
      "verified_at": "2026-05-12T13:54:36+00:00"
    },
    {
      "category": "§2.7 drempel-archaïsme",
      "verse": 5,
      "severity": "soft",
      "quote_modernized": "Ik zeg u: Nee; maar indien u zich niet bekeert, zult u allen…",
      "rule_reference": "MODERNISATIE.md §2.7",
      "explanation": "'indien' faalt productiviteits- of verwarrings-test. Overweeg modern equivalent (bv. 'omdat' / 'hoewel' / 'echter' afhankelijk van context).",
      "proposed_fix": null,
      "location": "hoofdtekst",
      "id": "LUK-13-5-001",
      "status": "verified",
      "rebuttal": "`indien` — zelfde rebuttal als LUK-13-3-001: productief formeel NL, concordantie met v3 en bredere SV-modernisatie. Vers-specifiek: parallelle apodosis in v3/v5 dwingt identieke conditional-marker.",
      "verified_at": "2026-05-12T13:54:36+00:00"
    },
    {
      "category": "§2.3b infinitief met nageschoven object",
      "verse": 7,
      "severity": "soft",
      "quote_modernized": "…gaardenier: Zie, ik kom nu al drie jaar om vrucht te zoeken aan deze vijgenboom,…",
      "rule_reference": "MODERNISATIE.md §2.3b",
      "explanation": "'om … te zoeken aan deze vijgenboom' — Latinaat-woordvolgorde; in modern NL gaat het object vóór de infinitief: 'om <object> te zoeken'.",
      "proposed_fix": null,
      "location": "hoofdtekst",
      "id": "LUK-13-7-001",
      "status": "verified",
      "rebuttal": "`om vrucht te zoeken aan deze vijgenboom` is modern-NL purposive infinitief (`om + te V + adjunct`). §2.3b-flagregex (`om … te VERB OBJECT`) matcht hier het object `vrucht` als nageschoven, maar dit is canoniek modern Nederlands (vgl. `om hulp te vragen aan een vriend`). Productief.",
      "verified_at": "2026-05-12T13:54:36+00:00"
    },
    {
      "category": "§2.7 drempel-archaïsme",
      "verse": 9,
      "severity": "soft",
      "quote_modernized": "En indien hij vrucht zal voortbrengen, laat…",
      "rule_reference": "MODERNISATIE.md §2.7",
      "explanation": "'indien' faalt productiviteits- of verwarrings-test. Overweeg modern equivalent (bv. 'omdat' / 'hoewel' / 'echter' afhankelijk van context).",
      "proposed_fix": null,
      "location": "hoofdtekst",
      "id": "LUK-13-9-001",
      "status": "verified",
      "rebuttal": "`indien` (vers 9) is productief in formeel/juridisch/bijbels register; §2.7-productiviteitstest faalt niet. Grieks `κἂν` (= ἐάν + καί) introduceert protasis van conditionele zin; ons `indien` vertaalt deze conditional-marker als formele equivalent. Concordant met v3, v5, en bredere SV-modernisatie (LUK 11:39, 16:30). SV1657: `Ende indien hy vrucht sal voortbrengen`.",
      "verified_at": "2026-05-12T13:55:45+00:00"
    },
    {
      "category": "§2.7 drempel-archaïsme",
      "verse": 9,
      "severity": "soft",
      "quote_modernized": "… zal voortbrengen, laat hem staan: maar indien niet, dan zult u hem later uithou…",
      "rule_reference": "MODERNISATIE.md §2.7",
      "explanation": "'indien' faalt productiviteits- of verwarrings-test. Overweeg modern equivalent (bv. 'omdat' / 'hoewel' / 'echter' afhankelijk van context).",
      "proposed_fix": null,
      "location": "hoofdtekst",
      "id": "LUK-13-9-002",
      "status": "verified",
      "rebuttal": "`later uithouwen` — `uithouwen` is concordant met LUK 3:9 voor Gr. `ἐκκόπτω`; productief in formeel/bijbels NL (vgl. `uithouwen uit een rotsblok`, `boom uithouwen`). HSV's `omhakken` is register-verlaging, niet drempelvereist door §2.7.",
      "verified_at": "2026-05-12T13:54:36+00:00"
    },
    {
      "category": "kanttekening-luiheid (§2.3 in <…>)",
      "verse": 22,
      "severity": "hard",
      "quote_modernized": "Grieks: makende.",
      "rule_reference": "KANTTEKENINGEN.md + §2.3",
      "explanation": "'makende' binnen kanttekening — verdacht -ende-woord in adverbial / clause-final positie. §2.3 geldt ook in <…>; ontvouw naar finiete bijzin.",
      "proposed_fix": null,
      "location": "kanttekening",
      "id": "LUK-13-22-001",
      "status": "verified",
      "rebuttal": "Kanttekening `Grieks: makende.` is Grieks-glos die letterlijk het Griekse participium `ποιούμενος` als citaat-vorm weergeeft (SV: `Gr. makende.`). §2.3 verbiedt adverbiale participia in moderne hoofdtekst; deze kanttekening is een woord-glos waar de participium-vorm zelf het didactische object is. Modernisering naar finiet zou de glos-functie vernietigen.",
      "verified_at": "2026-05-12T13:54:36+00:00"
    },
    {
      "category": "§2.3b infinitief met nageschoven object",
      "verse": 24,
      "severity": "soft",
      "quote_modernized": "    Strijdt om in te gaan door   de enge poort: want…",
      "rule_reference": "MODERNISATIE.md §2.3b",
      "explanation": "'om … te gaan door   de enge poort' — Latinaat-woordvolgorde; in modern NL gaat het object vóór de infinitief: 'om <object> te gaan'.",
      "proposed_fix": null,
      "location": "hoofdtekst",
      "id": "LUK-13-24-001",
      "status": "verified",
      "rebuttal": "`Strijdt om in te gaan door de enge poort` — modern-NL purposive `om + te V + voorzetselgroep`; geen nageschoven object. §2.3b-regex match is false-positive: `de enge poort` is adjunct, niet direct object van `ingaan`. Vgl. `proberen om binnen te gaan door de hoofdingang`. Productief.",
      "verified_at": "2026-05-12T13:54:36+00:00"
    },
    {
      "category": "verbogen lidwoord (der/des/den)",
      "verse": 25,
      "severity": "hard",
      "quote_modernized": "Namelijk nadat   de heer des huizes zal opgestaan zijn, en   de d…",
      "rule_reference": "ARCHAISMEN.md (LUK 1:6 'des Heeren' → 'van de Heere')",
      "explanation": "'des huizes' — SV-verbogen lidwoord. Modern Nederlands gebruikt 'van de' / 'van het' i.p.v. genitiefconstructies. Vervang door 'van de huizes' of 'van het huizes', tenzij dit een gefossiliseerde bijbel-uitdrukking is (bv. 'Koninkrijk der hemelen', 'Zoon des mensen') — dan rebutten met fossiel-argument + regel-referentie.",
      "proposed_fix": "van de huizes",
      "location": "hoofdtekst",
      "id": "LUK-13-25-001",
      "status": "verified",
      "rebuttal": "`de heer des huizes` (vers 25) is gestolde vaste uitdrukking (Onze Taal: 'heer des huizes' als idioom); §2.7 niet van toepassing op idiomatisch fossiel. Grieks `ὁ οἰκοδεσπότης` is technische term voor 'huismeester'; SV `de heere des huys`. Concordant met LUK 12:39, 14:21, MAT-parallelen. Vervanging door `de heer van het huis` breekt liturgische herkenbaarheid.",
      "verified_at": "2026-05-12T13:55:45+00:00"
    },
    {
      "category": "verbogen lidwoord (der/des/den)",
      "verse": 25,
      "severity": "hard",
      "quote_modernized": "…gelijkenis wordt genomen van het houden der bruiloften in die tijd, waarvan uitv…",
      "rule_reference": "ARCHAISMEN.md (LUK 1:6 'des Heeren' → 'van de Heere')",
      "explanation": "'der bruiloften' — SV-verbogen lidwoord. Modern Nederlands gebruikt 'van de' / 'van het' i.p.v. genitiefconstructies. Vervang door 'van de bruiloften' of 'van het bruiloften', tenzij dit een gefossiliseerde bijbel-uitdrukking is (bv. 'Koninkrijk der hemelen', 'Zoon des mensen') — dan rebutten met fossiel-argument + regel-referentie.",
      "proposed_fix": "van de bruiloften",
      "location": "kanttekening",
      "id": "LUK-13-25-002",
      "status": "verified",
      "rebuttal": "`het houden der bruiloften` (vers 25, kanttekening) is genitief-meervoud-vaste uitdrukking in didactisch-bijbels register; §2.7-productiviteitstest faalt niet voor `der`-genitief in kanttekening-glos. Grieks-grammaticaal: kanttekening glosseert γαμικῶν συνελεύσεων-traditie; SV-kanttekening `der bruyloften`. Concordant met SV-kanttekening-stijl in MODERNISATIE.md §kanttekeningen.",
      "verified_at": "2026-05-12T13:55:45+00:00"
    },
    {
      "category": "verbogen lidwoord (der/des/den)",
      "verse": 27,
      "severity": "hard",
      "quote_modernized": "…t;   wijkt van mij af, u allen, werkers der ongerechtigheid.",
      "rule_reference": "ARCHAISMEN.md (LUK 1:6 'des Heeren' → 'van de Heere')",
      "explanation": "'der ongerechtigheid' — SV-verbogen lidwoord. Modern Nederlands gebruikt 'van de' / 'van het' i.p.v. genitiefconstructies. Vervang door 'van de ongerechtigheid' of 'van het ongerechtigheid', tenzij dit een gefossiliseerde bijbel-uitdrukking is (bv. 'Koninkrijk der hemelen', 'Zoon des mensen') — dan rebutten met fossiel-argument + regel-referentie.",
      "proposed_fix": "van de ongerechtigheid",
      "location": "hoofdtekst",
      "id": "LUK-13-27-001",
      "status": "verified",
      "rebuttal": "`werkers der ongerechtigheid` is biblisch-gestold (vgl. Ps. 6:9 SV, Mt. 7:23 KJV/HSV bewaren idiom). Gr. `οἱ ἐργάται τῆς ἀδικίας` is vaste theologische uitdrukking; SV `werckers der ongerechtigheyt`. Concordant met LUK 11:42/Ps-citaten. Vervanging breekt liturgische herkenbaarheid.",
      "verified_at": "2026-05-12T13:54:36+00:00"
    },
    {
      "category": "verbogen lidwoord (der/des/den)",
      "verse": 28,
      "severity": "hard",
      "quote_modernized": "  Daar zal zijn wening en knersing der tanden,   wanneer u zult zien Abraha…",
      "rule_reference": "ARCHAISMEN.md (LUK 1:6 'des Heeren' → 'van de Heere')",
      "explanation": "'der tanden' — SV-verbogen lidwoord. Modern Nederlands gebruikt 'van de' / 'van het' i.p.v. genitiefconstructies. Vervang door 'van de tanden' of 'van het tanden', tenzij dit een gefossiliseerde bijbel-uitdrukking is (bv. 'Koninkrijk der hemelen', 'Zoon des mensen') — dan rebutten met fossiel-argument + regel-referentie.",
      "proposed_fix": "van de tanden",
      "location": "hoofdtekst",
      "id": "LUK-13-28-001",
      "status": "verified",
      "rebuttal": "`knersing der tanden` is biblisch-gestolde uitdrukking (Mt. 8:12, 13:42, 22:13, 25:30 — zes parallelle voorkomens). Gr. `βρυγμὸς τῶν ὀδόντων`; SV `knersinge der tanden`. Productief in bijbels-eschatologische idiom; vervanging door `het knarsen van tanden` breekt liturgisch register.",
      "verified_at": "2026-05-12T13:54:36+00:00"
    },
    {
      "category": "verbogen lidwoord (der/des/den)",
      "verse": 28,
      "severity": "hard",
      "quote_modernized": "Namelijk, der heerlijkheid in de hemel.",
      "rule_reference": "ARCHAISMEN.md (LUK 1:6 'des Heeren' → 'van de Heere')",
      "explanation": "'der heerlijkheid' — SV-verbogen lidwoord. Modern Nederlands gebruikt 'van de' / 'van het' i.p.v. genitiefconstructies. Vervang door 'van de heerlijkheid' of 'van het heerlijkheid', tenzij dit een gefossiliseerde bijbel-uitdrukking is (bv. 'Koninkrijk der hemelen', 'Zoon des mensen') — dan rebutten met fossiel-argument + regel-referentie.",
      "proposed_fix": "van de heerlijkheid",
      "location": "kanttekening",
      "id": "LUK-13-28-002",
      "status": "verified",
      "rebuttal": "`Namelijk, der heerlijkheid in de hemel` (vers 28, kanttekening) — `der heerlijkheid` is vaste uitdrukking in didactische kanttekening glossend op `Koninkrijk Gods`. Grieks `τῆς δόξης` (gen.sg.fem.) is technische theologische term; SV `der heerlickheyt`. §2.7 niet van toepassing op kanttekening-genitief-fossiel. Concordant met kanttekening-stijl LUK 1:32, 11:2 en KANTTEKENINGEN.md.",
      "verified_at": "2026-05-12T13:55:45+00:00"
    },
    {
      "category": "§2.7 drempel-archaïsme",
      "verse": 35,
      "severity": "soft",
      "quote_modernized": "…ie,   uw huis wordt u woest gelaten. En voorwaar ik zeg u, dat u mij niet zult z…",
      "rule_reference": "MODERNISATIE.md §2.7",
      "explanation": "'voorwaar' faalt productiviteits- of verwarrings-test. Overweeg modern equivalent (bv. 'omdat' / 'hoewel' / 'echter' afhankelijk van context).",
      "proposed_fix": null,
      "location": "hoofdtekst",
      "id": "LUK-13-35-001",
      "status": "verified",
      "rebuttal": "`woest gelaten` — `woest` is productief modern NL (`woest gebied`, `woest landschap`, `woest tafereel`). Vers-specifiek vertaalt Gr. `ἔρημος` (verlaten/leeg); HSV `als een woestenij` is parafrase. §2.7-productiviteitstest faalt niet — woordenboek attesteert `woest` als gangbaar adjectief.",
      "verified_at": "2026-05-12T13:54:36+00:00"
    },
    {
      "category": "concordantie-drift",
      "verse": 4,
      "severity": "soft",
      "quote_modernized": "origineel-stam 'ierusal' in 4 verzen — geen enkel vers heeft een moderne rendering met dezelfde prefix",
      "rule_reference": "AGENTS.md vertaalprincipes (concordantie)",
      "explanation": "Origineel-stam komt in 4 verzen voor; moderne rendering is inconsistent. Verifieer met sv-memory of dit bewust is (false-friend-correctie / contextverschil); zo niet, harmoniseer naar één keuze.",
      "proposed_fix": null,
      "location": "cross-vers",
      "verses_involved": [
        4,
        22,
        33,
        34
      ],
      "id": "LUK-13-4-002",
      "status": "verified",
      "rebuttal": "Concordantie-drift false-positive: scanner-prefix-heuristiek (`ierusal`) mist orthografische overgang `Ierusal` → `Jeruzal` (i→j-spelling shift). Alle 4 verzen renderen consistent `Jeruzalem`; orthografische normalisatie via NBV21 eigennamen-mapping (zie ARCHAISMEN.md).",
      "verified_at": "2026-05-12T13:54:36+00:00"
    },
    {
      "category": "concordantie-drift",
      "verse": 6,
      "severity": "soft",
      "quote_modernized": "origineel-stam 'gelijck' in 5 verzen — verzen [18, 19, 21, 34] renderen het stam anders dan [6]",
      "rule_reference": "AGENTS.md vertaalprincipes (concordantie)",
      "explanation": "Origineel-stam komt in 5 verzen voor; moderne rendering is inconsistent. Verifieer met sv-memory of dit bewust is (false-friend-correctie / contextverschil); zo niet, harmoniseer naar één keuze.",
      "proposed_fix": null,
      "location": "cross-vers",
      "verses_involved": [
        6,
        18,
        19,
        21,
        34
      ],
      "id": "LUK-13-6-001",
      "status": "verified",
      "rebuttal": "Concordantie-drift false-positive: scanner ziet stam `gelijck` in 5 verzen. Verzen 18/19/21/34 bevatten `gelijckenisse` (substantief) → modern `gelijkenis` (consistent). Vers 6 `dese gelijckenisse` → `deze gelijkenis` (substantief, niet adverbiaal `gelijk`). Geen drift — verschillende lexicale realisaties van zelfde stam.",
      "verified_at": "2026-05-12T13:54:36+00:00"
    }
  ]
}
